GazeParser/Configuration.py
GazeParser/Converter.py
GazeParser/Core.py
GazeParser/GazeParser.cfg
GazeParser/Graphics.py
GazeParser/LICENSE.txt
GazeParser/MicroSaccade.py
GazeParser/Region.py
GazeParser/ScanMatch.py
GazeParser/TrackingTools/Controller/Base.py
GazeParser/TrackingTools/Controller/DummyPsychoPyBackend.py
GazeParser/TrackingTools/Controller/PsychoPyBackend.py
GazeParser/TrackingTools/Controller/TrackingTools.cfg
GazeParser/TrackingTools/__init__.py
GazeParser/TrajectoryCurvature.py
GazeParser/Utility.py
GazeParser/__init__.py
GazeParser/app/CUIConverter.py
GazeParser/app/CameraDelayEstimator.py
GazeParser/app/ScanMatchMatricesFromImage.py
GazeParser/app/Viewer.py
GazeParser/app/__init__.py
GazeParser/app/_dialogs.py
GazeParser/app/img/combine.png
GazeParser/app/img/cood.png
GazeParser/app/img/gazeparser_viewer.gif
GazeParser/app/img/gazeparser_viewer.xpm
GazeParser/app/img/icons.svg
GazeParser/app/img/next.png
GazeParser/app/img/next_disabled.png
GazeParser/app/img/open.png
GazeParser/app/img/previous.png
GazeParser/app/img/previous_disabled.png
GazeParser/app/img/saveas.png
GazeParser/app/img/viewer.ico
GazeParser/app/img/viewer.png
GazeParser/app/img/white800x600.png
GazeParser/app/img/zoomin.png
GazeParser/app/img/zoomout.png
GazeParser/app/viewer.cfg
GazeParser/tests/data/test01.csv
GazeParser/tests/data/test01_noConf_useFP_ref.db
GazeParser/tests/data/test01_noconf_usefp.db
GazeParser/tests/data/test01_testconf01_nofp.db
GazeParser/tests/data/test01_testconf01_nofp_ref.db
GazeParser/tests/data/test01_testconf01_usefp.db
GazeParser/tests/data/test01_testconf01_usefp_ref.db
GazeParser/tests/data/test02.csv
GazeParser/tests/data/test02_noconf_usefp.db
GazeParser/tests/data/test02_testconf02_nofp.db
GazeParser/tests/data/test03_ptc.tsv
GazeParser/tests/data/test03_ptc_testconf03.db
GazeParser/tests/data/test_0.6.5.db
GazeParser/tests/data/testconf01.cfg
GazeParser/tests/data/testconf02.cfg
GazeParser/tests/data/testconf03.cfg
gazeparser-0.12.2.dist-info/METADATA
gazeparser-0.12.2.dist-info/WHEEL
gazeparser-0.12.2.dist-info/entry_points.txt
gazeparser-0.12.2.dist-info/RECORD
