Metadata-Version: 2.1
Name: GazeParser
Version: 0.12.2
Summary: Gaze tracking, parsing and visualization tools
Author-Email: Hiroyuki Sogo <hsogo12600@gmail.com>>
Maintainer-Email: Hiroyuki Sogo <hsogo12600@gmail.com>>
Classifier: Development Status :: 4 - Beta
Classifier: Operating System :: Microsoft :: Windows
Classifier: Operating System :: POSIX :: Linux
Classifier: Programming Language :: Python :: 3
Classifier: Topic :: Scientific/Engineering
Classifier: License :: OSI Approved :: GNU General Public License v3 or later (GPLv3+)
Project-URL: Homepage, https://github.com/hsogo/gazeparser
Requires-Python: >=3.8
Requires-Dist: numpy
Requires-Dist: scipy
Requires-Dist: matplotlib
Requires-Dist: wxpython
